GaoxiaonengRenshideQigeXiguan/README.md
GaoxiaonengRenshideQigeXiguan/__init__.py
GaoxiaonengRenshideQigeXiguan/__main__.py
GaoxiaonengRenshideQigeXiguan/file.epub
GaoxiaonengRenshideQigeXiguan/index.html
GaoxiaonengRenshideQigeXiguan/css/__init__.py
GaoxiaonengRenshideQigeXiguan/css/annotations.css
GaoxiaonengRenshideQigeXiguan/css/main.css
GaoxiaonengRenshideQigeXiguan/css/normalize.css
GaoxiaonengRenshideQigeXiguan/css/popup.css
GaoxiaonengRenshideQigeXiguan/font/__init__.py
GaoxiaonengRenshideQigeXiguan/font/fontello.eot
GaoxiaonengRenshideQigeXiguan/font/fontello.svg
GaoxiaonengRenshideQigeXiguan/font/fontello.ttf
GaoxiaonengRenshideQigeXiguan/font/fontello.woff
GaoxiaonengRenshideQigeXiguan/img/__init__.py
GaoxiaonengRenshideQigeXiguan/img/annotator-glyph-sprite.png
GaoxiaonengRenshideQigeXiguan/img/annotator-icon-sprite.png
GaoxiaonengRenshideQigeXiguan/img/apple-touch-icon.png
GaoxiaonengRenshideQigeXiguan/img/cancelfullscreen.png
GaoxiaonengRenshideQigeXiguan/img/close.png
GaoxiaonengRenshideQigeXiguan/img/fullscreen.png
GaoxiaonengRenshideQigeXiguan/img/loader.gif
GaoxiaonengRenshideQigeXiguan/img/menu-icon.png
GaoxiaonengRenshideQigeXiguan/img/save.png
GaoxiaonengRenshideQigeXiguan/img/saved.png
GaoxiaonengRenshideQigeXiguan/img/settings-s.png
GaoxiaonengRenshideQigeXiguan/img/settings.png
GaoxiaonengRenshideQigeXiguan/img/star.png
GaoxiaonengRenshideQigeXiguan/js/__init__.py
GaoxiaonengRenshideQigeXiguan/js/epub.js
GaoxiaonengRenshideQigeXiguan/js/epub.min.js
GaoxiaonengRenshideQigeXiguan/js/epub.min.map
GaoxiaonengRenshideQigeXiguan/js/hooks.min.js
GaoxiaonengRenshideQigeXiguan/js/hooks.min.map
GaoxiaonengRenshideQigeXiguan/js/reader.js
GaoxiaonengRenshideQigeXiguan/js/reader.js.map
GaoxiaonengRenshideQigeXiguan/js/reader.min.js
GaoxiaonengRenshideQigeXiguan/js/reader.min.map
GaoxiaonengRenshideQigeXiguan/js/hooks/__init__.py
GaoxiaonengRenshideQigeXiguan/js/hooks/extensions/__init__.py
GaoxiaonengRenshideQigeXiguan/js/hooks/extensions/highlight.js
gaoxiaoneng_renshide_qige_xiguan-2022.10.15.0.dist-info/METADATA
gaoxiaoneng_renshide_qige_xiguan-2022.10.15.0.dist-info/WHEEL
gaoxiaoneng_renshide_qige_xiguan-2022.10.15.0.dist-info/entry_points.txt
gaoxiaoneng_renshide_qige_xiguan-2022.10.15.0.dist-info/top_level.txt
gaoxiaoneng_renshide_qige_xiguan-2022.10.15.0.dist-info/RECORD
